yt_dlpp/__init__.py
yt_dlpp/main.py
yt_dlpp/interceptors/__init__.py
yt_dlpp/interceptors/interceptor.py
yt_dlpp/workers/__init__.py
yt_dlpp/workers/dedup_worker.py
yt_dlpp/workers/download_worker.py
yt_dlpp/workers/info_worker.py
yt_dlpp/workers/progress_worker.py
yt_dlpp/workers/worker.py
yt_dlpp-1.0.2.dist-info/LICENSE.md
yt_dlpp-1.0.2.dist-info/METADATA
yt_dlpp-1.0.2.dist-info/WHEEL
yt_dlpp-1.0.2.dist-info/entry_points.txt
yt_dlpp-1.0.2.dist-info/top_level.txt
yt_dlpp-1.0.2.dist-info/RECORD
