Metadata-Version: 2.1
Name: yt-dlpp
Version: 1.0.2
Summary: A thin wrapper around yt-dlp for parallel downloads
Author-email: Geoffrey Coulaud <geoffrey.coulaud@gmail.com>
License: This is free and unencumbered software released into the public domain.
Project-URL: Homepage, https://github.com/GeoffreyCoulaud/yt-dlpp
Project-URL: Repository, https://github.com/GeoffreyCoulaud/yt-dlpp.git
Keywords: download,yt-dlp,video,audio,parallel
Classifier: License :: OSI Approved :: The Unlicense (Unlicense)
Classifier: Programming Language :: Python :: 3.11
Classifier: Programming Language :: Python :: 3
Requires-Python: >=3.11
License-File: LICENSE.md
Requires-Dist: rich
